init/__init__.py
airsim_autonomous_landing-0.1.1.dist-info/METADATA
airsim_autonomous_landing-0.1.1.dist-info/WHEEL
airsim_autonomous_landing-0.1.1.dist-info/top_level.txt
airsim_autonomous_landing-0.1.1.dist-info/RECORD
