Metadata-Version: 2.1
Name: airsim-autonomous-landing
Version: 0.1.1
Summary: easy to use autonomous landing package for airsim
Home-page: https://github.com/RazGavrieli/Autonomous-Drone-Landing-On-Moving-Object-AirSim
Author: Raz Gavrieli
Author-email: razgavrieli@gmail.com
License: MIT
Requires-Dist: airsim (==1.8.1)
Requires-Dist: numpy (==1.23.3)
